basekkkk/__init__.py
basekkkk/player.py
basekkkk/team.py
basekkkk/team_wl.py
basekkkk-0.0.0.2.dist-info/METADATA
basekkkk-0.0.0.2.dist-info/WHEEL
basekkkk-0.0.0.2.dist-info/top_level.txt
basekkkk-0.0.0.2.dist-info/RECORD
